kinto_signer/__init__.py
kinto_signer/events.py
kinto_signer/generate_keypair.py
kinto_signer/hasher.py
kinto_signer/listeners.py
kinto_signer/serializer.py
kinto_signer/updater.py
kinto_signer/utils.py
kinto_signer/signer/__init__.py
kinto_signer/signer/autograph.py
kinto_signer/signer/base.py
kinto_signer/signer/exceptions.py
kinto_signer/signer/local_ecdsa.py
tests/__init__.py
tests/functional.py
tests/support.py
tests/test_events.py
tests/test_generate_keypair.py
tests/test_hasher.py
tests/test_plugin_setup.py
tests/test_serializer.py
tests/test_signer.py
tests/test_signer_attachments.py
tests/test_signoff_flow.py
tests/test_updater.py
tests/test_utils.py
kinto_signer-8.1.1.dist-info/METADATA
kinto_signer-8.1.1.dist-info/WHEEL
kinto_signer-8.1.1.dist-info/top_level.txt
kinto_signer-8.1.1.dist-info/RECORD
