Metadata-Version: 2.1
Name: kinto-signer
Version: 8.1.1
Summary: Kinto signer
Home-page: UNKNOWN
Author: Mozilla Services
Author-email: services-dev@mozilla.com
License: Apache License (2.0)
Keywords: web services
Platform: UNKNOWN
Classifier: Development Status :: 7 - Inactive
Classifier: Programming Language :: Python
Classifier: Programming Language :: Python :: 3
Classifier: Programming Language :: Python :: 3.5
Classifier: Programming Language :: Python :: 3.6
Classifier: Programming Language :: Python :: Implementation :: CPython
Classifier: Topic :: Internet :: WWW/HTTP
Classifier: Topic :: Internet :: WWW/HTTP :: WSGI :: Application
Classifier: License :: OSI Approved :: Apache Software License
Requires-Dist: kinto (>=12.0.1)
Requires-Dist: boto3
Requires-Dist: canonicaljson-rs
Requires-Dist: ecdsa
Requires-Dist: requests-hawk
